axiomic/__init__.py
axiomic/constants.py
axiomic/core_config.py
axiomic/errors.py
axiomic/configure/__init__.py
axiomic/configure/default_config.py
axiomic/configure/default_config_explainers.py
axiomic/configure/runtime_config.py
axiomic/contrib/__init__.py
axiomic/core/__init__.py
axiomic/core/checks/__init__.py
axiomic/core/checks/core_checks.py
axiomic/core/knits/__init__.py
axiomic/core/knits/chat.py
axiomic/core/knits/enforce_jsonschema.py
axiomic/core/knits/json_pattern.py
axiomic/core/knits/pattern.py
axiomic/core/knits/switch.py
axiomic/core/knits/switch_test.py
axiomic/core/uagents/__init__.py
axiomic/core/uagents/list_sort.py
axiomic/core/uagents/pydantic_pattern.py
axiomic/core/uagents/pydantic_pattern_test.py
axiomic/data/__init__.py
axiomic/data/aembedding.py
axiomic/data/aimage.py
axiomic/data/convert.py
axiomic/data/lists.py
axiomic/data/loaders.py
axiomic/data/loaders_test.py
axiomic/data/schema.py
axiomic/data/validate.py
axiomic/engine/__init__.py
axiomic/engine/exec_context.py
axiomic/engine/execute.py
axiomic/engine/functional.py
axiomic/engine/node_map.py
axiomic/engine/record.py
axiomic/engine/node_impls/__init__.py
axiomic/engine/node_impls/boolean_gate.py
axiomic/engine/node_impls/builtin_binary_check_node.py
axiomic/engine/node_impls/builtin_binary_checks.py
axiomic/engine/node_impls/builtin_unary_check_node.py
axiomic/engine/node_impls/builtin_unary_checks.py
axiomic/engine/node_impls/flat_rag_topk_node.py
axiomic/engine/node_impls/format_node.py
axiomic/engine/node_impls/history_complete.py
axiomic/engine/node_impls/immediate.py
axiomic/engine/node_impls/name_node.py
axiomic/engine/node_impls/txt_to_img_node.py
axiomic/frontend/__init__.py
axiomic/frontend/config.py
axiomic/frontend/embedding.py
axiomic/frontend/expand.py
axiomic/frontend/functions.py
axiomic/frontend/image.py
axiomic/frontend/params.py
axiomic/frontend/string_list.py
axiomic/frontend/text.py
axiomic/graph/__init__.py
axiomic/graph/tree.py
axiomic/logalytics/__init__.py
axiomic-0.0.2.dist-info/LICENSE
axiomic-0.0.2.dist-info/METADATA
axiomic-0.0.2.dist-info/WHEEL
axiomic-0.0.2.dist-info/entry_points.txt
axiomic-0.0.2.dist-info/top_level.txt
axiomic-0.0.2.dist-info/RECORD
